astuce/__init__.py
astuce/_assigned_statements.py
astuce/_astunparse.py
astuce/_context.py
astuce/_decorators.py
astuce/_filter_statements.py
astuce/_inference_decorators.py
astuce/_lookup.py
astuce/_monkey.py
astuce/_typing.py
astuce/exceptions.py
astuce/inference.py
astuce/nodes.py
astuce/parser.py
astuce-0.0.2.dist-info/LICENSE
astuce-0.0.2.dist-info/METADATA
astuce-0.0.2.dist-info/WHEEL
astuce-0.0.2.dist-info/top_level.txt
astuce-0.0.2.dist-info/RECORD
