Metadata-Version: 2.1
Name: astuce
Version: 0.0.2
Summary: AST inference utilities.
Home-page: https://github.com/tristanlatr/astuce
Author: Various contributors
License: GNU LESSER GENERAL PUBLIC LICENSE Version 2.1
Keywords: static code analysis,python,abstract syntax tree
Requires-Python: >=3.7.2
License-File: LICENSE
Requires-Dist: attrs
Requires-Dist: cached-property ; python_version < "3.8"
Provides-Extra: docs
Requires-Dist: pydoctor ; extra == 'docs'
Provides-Extra: test
Requires-Dist: attrs ; extra == 'test'
Requires-Dist: coverage ; extra == 'test'
Requires-Dist: pytest ; extra == 'test'
Requires-Dist: astor ; extra == 'test'
